libzapi/__init__.py
libzapi/application/__init__.py
libzapi/application/commands/__init__.py
libzapi/application/commands/help_center/__init__.py
libzapi/application/commands/help_center/account_custom_claim_cmds.py
libzapi/application/commands/help_center/category_cmds.py
libzapi/application/commands/help_center/section_cmds.py
libzapi/application/commands/help_center/user_segments_cmds.py
libzapi/application/commands/ticketing/__init__.py
libzapi/application/commands/ticketing/group_cmds.py
libzapi/application/commands/ticketing/ticket_cmds.py
libzapi/application/services/__init__.py
libzapi/application/services/custom_data/__init__.py
libzapi/application/services/custom_data/custom_object_fields_service.py
libzapi/application/services/custom_data/custom_object_records.py
libzapi/application/services/custom_data/custom_objects_service.py
libzapi/application/services/help_center/__init__.py
libzapi/application/services/help_center/account_custom_claims_service.py
libzapi/application/services/help_center/article_attachments_service.py
libzapi/application/services/help_center/articles_service.py
libzapi/application/services/help_center/categories_service.py
libzapi/application/services/help_center/sections_service.py
libzapi/application/services/help_center/user_segments_service.py
libzapi/application/services/ticketing/__init__.py
libzapi/application/services/ticketing/account_settings_service.py
libzapi/application/services/ticketing/attachments_service.py
libzapi/application/services/ticketing/automations_service.py
libzapi/application/services/ticketing/brand_agents_service.py
libzapi/application/services/ticketing/brands_service.py
libzapi/application/services/ticketing/email_notifications_service.py
libzapi/application/services/ticketing/groups_service.py
libzapi/application/services/ticketing/macro_service.py
libzapi/application/services/ticketing/organizations_service.py
libzapi/application/services/ticketing/requests_service.py
libzapi-0.6.0.dist-info/METADATA
libzapi-0.6.0.dist-info/WHEEL
libzapi-0.6.0.dist-info/licenses/LICENSE
libzapi-0.6.0.dist-info/RECORD
