Metadata-Version: 2.4
Name: libzapi
Version: 0.6.0
Summary: Python client for the Zendesk API
Project-URL: Homepage, https://github.com/BCR-CX/libzapi
Project-URL: Issues, https://github.com/BCR-CX/libzapi/issues
Author-email: Leandro Meili <leandro.meili@bcrcx.com>
License-Expression: MIT
License-File: LICENSE
Keywords: api,sdk,zendesk
Classifier: Development Status :: 2 - Pre-Alpha
Classifier: Intended Audience :: Customer Service
Classifier: Intended Audience :: Developers
Classifier: Intended Audience :: Information Technology
Classifier: License :: OSI Approved :: MIT License
Classifier: Operating System :: OS Independent
Classifier: Programming Language :: Python :: 3 :: Only
Classifier: Programming Language :: Python :: 3.12
Classifier: Programming Language :: Python :: 3.13
Classifier: Programming Language :: Python :: 3.14
Classifier: Programming Language :: Python :: 3.15
Classifier: Topic :: Internet :: WWW/HTTP
Classifier: Topic :: Software Development :: Libraries
Classifier: Topic :: Software Development :: Libraries :: Python Modules
Requires-Python: >=3.12
Requires-Dist: cattrs>=25.3.0
Requires-Dist: requests>=2.32.5
Provides-Extra: test
Requires-Dist: hypothesis>=6.147.0; extra == 'test'
Requires-Dist: mypy; extra == 'test'
Requires-Dist: pytest-cov; extra == 'test'
Requires-Dist: pytest-mock>=3.15.1; extra == 'test'
Requires-Dist: pytest>=8; extra == 'test'
Requires-Dist: ruff; extra == 'test'
